fizzbuzz/__fizzbuzz__.py
fizzbuzz/__init__.py
fizzbuzz/__lib.py
fizzbuzz/__lib__.py
fizzbuzz/__main__.py
fizzbuzz/fizzbuzz.py
fizzbuzz/main.py
fizzbuzz2-2.1.16.dist-info/LICENSE
fizzbuzz2-2.1.16.dist-info/METADATA
fizzbuzz2-2.1.16.dist-info/WHEEL
fizzbuzz2-2.1.16.dist-info/entry_points.txt
fizzbuzz2-2.1.16.dist-info/top_level.txt
fizzbuzz2-2.1.16.dist-info/RECORD
