Metadata-Version: 2.1
Name: fizzbuzz2
Version: 2.1.16
Summary: Powerful Fizz Buzz Engine
Home-page: https://github.com/nbtk/fizzbuzz
Author: nbtk
License: BSD
Platform: UNKNOWN
Classifier: Development Status :: 4 - Beta
Classifier: Programming Language :: Python :: 3
Classifier: License :: OSI Approved :: BSD License
Requires-Python: >=3.7
License-File: LICENSE
